yubikey.py
awsume_yubikey_plugin-1.2.5.dist-info/LICENSE
awsume_yubikey_plugin-1.2.5.dist-info/METADATA
awsume_yubikey_plugin-1.2.5.dist-info/WHEEL
awsume_yubikey_plugin-1.2.5.dist-info/entry_points.txt
awsume_yubikey_plugin-1.2.5.dist-info/top_level.txt
awsume_yubikey_plugin-1.2.5.dist-info/RECORD
